shellman-1.0.2.dist-info/METADATA
shellman-1.0.2.dist-info/WHEEL
shellman-1.0.2.dist-info/entry_points.txt
shellman-1.0.2.dist-info/licenses/LICENSE
shellman/__init__.py
shellman/__main__.py
shellman/_internal/__init__.py
shellman/_internal/cli.py
shellman/_internal/context.py
shellman/_internal/debug.py
shellman/_internal/reader.py
shellman/_internal/tags.py
shellman/_internal/templates/__init__.py
shellman/_internal/templates/data/helptext
shellman/_internal/templates/data/helptext_function
shellman/_internal/templates/data/manpage.groff
shellman/_internal/templates/data/manpage.md
shellman/_internal/templates/data/manpage_function.groff
shellman/_internal/templates/data/manpage_function.md
shellman/_internal/templates/data/usagetext
shellman/_internal/templates/data/wikipage.md
shellman/_internal/templates/data/wikipage_function.md
shellman/_internal/templates/data/wikipage_toc.md
shellman/_internal/templates/filters.py
shellman/cli.py
shellman/context.py
shellman/py.typed
shellman/reader.py
shellman/tags.py
shellman/templates/__init__.py
shellman/templates/filters.py
shellman-1.0.2.dist-info/RECORD
