Metadata-Version: 2.4
Name: shellman
Version: 1.0.2
Summary: Write documentation in comments and render it with templates.
Author-Email: =?utf-8?q?Timoth=C3=A9e_Mazzucotelli?= <dev@pawamoy.fr>
License-Expression: ISC
License-File: LICENSE
Classifier: Development Status :: 4 - Beta
Classifier: Intended Audience :: Developers
Classifier: Programming Language :: Python
Classifier: Programming Language :: Python :: 3
Classifier: Programming Language :: Python :: 3 :: Only
Classifier: Programming Language :: Python :: 3.9
Classifier: Programming Language :: Python :: 3.10
Classifier: Programming Language :: Python :: 3.11
Classifier: Programming Language :: Python :: 3.12
Classifier: Programming Language :: Python :: 3.13
Classifier: Programming Language :: Python :: 3.14
Classifier: Topic :: Documentation
Classifier: Topic :: Software Development
Classifier: Topic :: Utilities
Classifier: Typing :: Typed
Project-URL: Homepage, https://pawamoy.github.io/shellman
Project-URL: Documentation, https://pawamoy.github.io/shellman
Project-URL: Changelog, https://pawamoy.github.io/shellman/changelog
Project-URL: Repository, https://github.com/pawamoy/shellman
Project-URL: Issues, https://github.com/pawamoy/shellman/issues
Project-URL: Discussions, https://github.com/pawamoy/shellman/discussions
Project-URL: Gitter, https://gitter.im/shellman/community
Project-URL: Funding, https://github.com/sponsors/pawamoy
Requires-Python: >=3.9
Requires-Dist: jinja2>=3
Requires-Dist: importlib-metadata>=4.6; python_version < "3.10"
Requires-Dist: typing-extensions>=4.0; python_version < "3.11"
